crabmd.py
crabmd-0.0.19.dist-info/DESCRIPTION.rst
crabmd-0.0.19.dist-info/METADATA
crabmd-0.0.19.dist-info/RECORD
crabmd-0.0.19.dist-info/WHEEL
crabmd-0.0.19.dist-info/metadata.json
crabmd-0.0.19.dist-info/top_level.txt
